MANIFEST.in
README.md
setup.cfg
setup.py
spacy_kenlm/__init__.py
spacy_kenlm/_about.py
spacy_kenlm/language_model.py
spacy_kenlm/test.arpa
spacy_kenlm.egg-info/PKG-INFO
spacy_kenlm.egg-info/SOURCES.txt
spacy_kenlm.egg-info/dependency_links.txt
spacy_kenlm.egg-info/not-zip-safe
spacy_kenlm.egg-info/requires.txt
spacy_kenlm.egg-info/top_level.txt