Metadata-Version: 1.0
Name: spacy-kenlm
Version: 0.1.1
Summary: spaCy extension for kenLM.
Home-page: https://github.com/tokestermw/spacy_kenlm
Author: Motoki Wu
Author-email: tokestermw@gmail.com
License: MIT
Platform: UNKNOWN
